jira_commands/__init__.py
jira_commands/cli/__init__.py
jira_commands/cli/common.py
jira_commands/cli/crudops.py
jira_commands/cli/jc.py
jira_commands/cli/jql.py
jira_commands/cli/labels.py
jira_commands/cli/list.py
jira_commands/cli/map_extractor.py
jira_commands/cli/subtasks.py
jira_commands/cli/vivisect.py
jira_commands/jira.py
jira_commands/utils.py
jira_commands-0.22.2.dist-info/LICENSE
jira_commands-0.22.2.dist-info/METADATA
jira_commands-0.22.2.dist-info/WHEEL
jira_commands-0.22.2.dist-info/entry_points.txt
jira_commands-0.22.2.dist-info/RECORD
