Metadata-Version: 2.1
Name: jira-commands
Version: 0.22.2
Summary: Command line utilities for interacting with JIRA
Home-page: https://github.com/unixorn/jira-commands
Author: Joe Block
Author-email: jpb@unixorn.net
Requires-Python: >=3.10,<4.0.0
Classifier: Programming Language :: Python :: 3
Classifier: Programming Language :: Python :: 3.10
Classifier: Programming Language :: Python :: 3.11
Classifier: Programming Language :: Python :: 3.12
Requires-Dist: PyYAML (>=6.0,<7.0)
Requires-Dist: cryptography (>=38.0.3,<43.0.0)
Requires-Dist: jira (>=3.1.1,<4.0.0)
Requires-Dist: thelogrus (>=0.7.0,<0.8.0)
Project-URL: Bug Tracker, https://github.com/unixorn/jira-commands/issues
Project-URL: Repository, https://github.com/unixorn/jira-commands
